{"namedChunkGroups":{"polyfill":{"name":"polyfill","assets":[{"name":"webpack-runtime-3e6b3b250c1d2122a58a.js","size":4421},{"name":"polyfill-eb6692359d26c085d694.js","size":82631}],"filteredAssets":0,"assetsSize":87052,"filteredAuxiliaryAssets":2,"auxiliaryAssetsSize":219135},"app":{"name":"app","assets":[{"name":"webpack-runtime-3e6b3b250c1d2122a58a.js","size":4421},{"name":"styles.549e3184c2af88e47968.css","size":9893},{"name":"framework-8e1f5a201c1d16fe999c.js","size":129732},{"name":"app-6e742faaf4fa8650f9eb.js","size":50593}],"filteredAssets":0,"assetsSize":194639,"filteredAuxiliaryAssets":3,"auxiliaryAssetsSize":548953},"component---src-pages-404-js":{"name":"component---src-pages-404-js","assets":[{"name":"component---src-pages-404-js-d446d26acad5acd012bd.js","size":722}],"filteredAssets":0,"assetsSize":722,"filteredAuxiliaryAssets":1,"auxiliaryAssetsSize":974},"component---src-pages-index-js":{"name":"component---src-pages-index-js","assets":[{"name":"styles.549e3184c2af88e47968.css","size":9893},{"name":"d64684d8-023576e9d5ecddc30dbc.js","size":1100},{"name":"1bfc9850-f6b0203faeb84341a278.js","size":4173},{"name":"component---src-pages-index-js-9f06a55aa053f367d72d.js","size":97144}],"filteredAssets":0,"assetsSize":112310,"filteredAuxiliaryAssets":3,"auxiliaryAssetsSize":2149623}},"assetsByChunkName":{"polyfill":["webpack-runtime-3e6b3b250c1d2122a58a.js","polyfill-eb6692359d26c085d694.js"],"app":["webpack-runtime-3e6b3b250c1d2122a58a.js","styles.549e3184c2af88e47968.css","framework-8e1f5a201c1d16fe999c.js","app-6e742faaf4fa8650f9eb.js"],"component---src-pages-404-js":["component---src-pages-404-js-d446d26acad5acd012bd.js"],"component---src-pages-index-js":["styles.549e3184c2af88e47968.css","d64684d8-023576e9d5ecddc30dbc.js","1bfc9850-f6b0203faeb84341a278.js","component---src-pages-index-js-9f06a55aa053f367d72d.js"]},"childAssetsByChunkName":{}}